funstrings/__init__.py
funstrings/__main__.py
funstrings/operations.py
funstrings-0.1.2.dist-info/licenses/LICENSE
tests/__init__.py
tests/test_new_functions.py
tests/test_new_operations.py
tests/test_operations.py
funstrings-0.1.2.dist-info/METADATA
funstrings-0.1.2.dist-info/WHEEL
funstrings-0.1.2.dist-info/entry_points.txt
funstrings-0.1.2.dist-info/top_level.txt
funstrings-0.1.2.dist-info/RECORD
