Metadata-Version: 2.4
Name: funstrings
Version: 0.1.2
Summary: A Python package for string manipulation and analysis, and to play with strings
Home-page: https://github.com/nilkanth02/funstrings
Download-URL: https://github.com/nilkanth02/funstrings/archive/v0.1.2.tar.gz
Author: Nilkanth Ahire
Author-email: nilkanth8747@gmail.com
License: MIT
Project-URL: Bug Tracker, https://github.com/nilkanth02/funstrings/issues
Project-URL: Documentation, https://github.com/nilkanth02/funstrings
Project-URL: Source Code, https://github.com/nilkanth02/funstrings
Project-URL: Examples, https://github.com/nilkanth02/funstrings/tree/main/examples
Project-URL: Educational Resources, https://github.com/nilkanth02/funstrings/tree/main/tutorials
Project-URL: Changelog, https://github.com/nilkanth02/funstrings/blob/main/CHANGELOG.md
Keywords: string,text,manipulation,utility,education,learning,beginner,student,playing,fun,easy_working
Classifier: Development Status :: 3 - Alpha
Classifier: Intended Audience :: Developers
Classifier: Intended Audience :: Education
Classifier: Intended Audience :: Science/Research
Classifier: License :: OSI Approved :: MIT License
Classifier: Natural Language :: English
Classifier: Operating System :: OS Independent
Classifier: Programming Language :: Python :: 3
Classifier: Programming Language :: Python :: 3.6
Classifier: Programming Language :: Python :: 3.7
Classifier: Programming Language :: Python :: 3.8
Classifier: Programming Language :: Python :: 3.9
Classifier: Programming Language :: Python :: 3.10
Classifier: Topic :: Software Development :: Libraries :: Python Modules
Classifier: Topic :: Text Processing :: General
Classifier: Topic :: Education :: Computer Aided Instruction (CAI)
Requires-Python: >=3.6
License-File: LICENSE
Provides-Extra: dev
Requires-Dist: pytest>=6.0; extra == "dev"
Requires-Dist: pytest-cov; extra == "dev"
Requires-Dist: flake8; extra == "dev"
Requires-Dist: black; extra == "dev"
Requires-Dist: sphinx; extra == "dev"
Requires-Dist: sphinx-rtd-theme; extra == "dev"
Provides-Extra: edu
Requires-Dist: jupyter; extra == "edu"
Requires-Dist: matplotlib; extra == "edu"
Dynamic: author
Dynamic: author-email
Dynamic: classifier
Dynamic: description
Dynamic: description-content-type
Dynamic: download-url
Dynamic: home-page
Dynamic: keywords
Dynamic: license
Dynamic: license-file
Dynamic: project-url
Dynamic: provides-extra
Dynamic: requires-python
Dynamic: summary
